LICENSE.txt
MANIFEST.in
README.md
setup.py
PortsScanner/PortsScanner.py
PortsScanner/TCPAsyncPortScanner.py
PortsScanner/TCPPortScanner.py
PortsScanner/__init__.py
PortsScanner.egg-info/PKG-INFO
PortsScanner.egg-info/SOURCES.txt
PortsScanner.egg-info/dependency_links.txt
PortsScanner.egg-info/entry_points.txt
PortsScanner.egg-info/top_level.txt