Metadata-Version: 2.1
Name: PortsScanner
Version: 0.0.1
Summary: This package implement a Ports Scanner.
Home-page: https://github.com/mauricelambert/PortsScanner
Author: Maurice Lambert
Author-email: mauricelambert434@gmail.com
Classifier: Programming Language :: Python
Classifier: Development Status :: 5 - Production/Stable
Classifier: Environment :: Console
Classifier: Natural Language :: English
Classifier: Operating System :: OS Independent
Classifier: Programming Language :: Python :: 3.8
Requires-Python: >=3.6
